{
  "id": "task-043-documentation-organization",
  "title": "Reorganize project documentation structure",
  "description": "Reorganizar toda la documentación del proyecto en una estructura coherente de carpetas para mejorar la navegabilidad y mantenibilidad. Consolidar archivos dispersos y actualizar referencias.\n\n**Problema Actual:**\n- Archivos de documentación esparcidos en el root del proyecto\n- Diferentes tipos de documentación mezclados\n- Dificulta encontrar información específica\n- No hay una estructura clara para contribuir nueva documentación\n\n**Nueva Estructura Propuesta:**\n```\ndocs/\n├── user-guide/           # Documentación para usuarios finales\n│   ├── README.md         # Movido desde root\n│   ├── INSTALL.md        # Guía de instalación\n│   ├── EXAMPLES.md       # Movido desde root\n│   └── FAQ.md            # Preguntas frecuentes\n├── development/          # Documentación para desarrolladores\n│   ├── BUILD.md          # Movido desde root\n│   ├── BUILD_PROCESS.md  # Movido desde root\n│   ├── DEVELOPMENT_STATUS.md  # Movido desde root\n│   ├── REACT_MIGRATION.md     # Movido desde root\n│   └── SCRIPTS_ORGANIZATION.md # Movido desde root\n├── testing/              # Documentación de testing\n│   ├── BINARY_TESTING.md # Movido desde root\n│   └── TESTING_GUIDE.md  # Guía general de testing\n├── architecture/         # Documentación técnica\n│   ├── EXPLAIN_FOR_AGENTS.md  # Movido desde root\n│   └── API_REFERENCE.md       # Futura documentación de API\n└── releases/            # Documentación de releases\n    ├── CHANGELOG.md     # Movido desde root\n    └── RELEASE_PROCESS.md # Proceso de releases\n```\n\n**Acciones Requeridas:**\n1. Crear estructura de carpetas `docs/`\n2. Mover archivos existentes a ubicaciones apropiadas\n3. Actualizar referencias internas entre documentos\n4. Crear archivo `docs/README.md` como índice principal\n5. Actualizar `.gitignore` si es necesario\n6. Verificar que no se rompan enlaces en GitHub/frontend\n\n**Tickets Relacionados que se Cierran:**\n- **task-004**: Create User Documentation (parcialmente)\n- **task-025**: Distribution Documentation (se organiza mejor)\n\n**Beneficios:**\n- Navegación más intuitiva\n- Separación clara por audiencia (users vs developers)\n- Estructura escalable para futuras contribuciones\n- Mejor experiencia para nuevos contributors\n- Facilita encontrar documentación específica",
  "state": "ready_to_release",
  "type": "documentation",
  "priority": "medium",
  "epic": "getting-started",
  "author": "default",
  "assignee": "default",
  "tags": ["documentation", "organization", "structure", "maintainability"],
  "subtasks": [
    {
      "id": "1",
      "text": "Crear estructura de carpetas docs/ con subcarpetas",
      "completed": true
    },
    {
      "id": "2", 
      "text": "Mover archivos de documentación a ubicaciones apropiadas",
      "completed": true
    },
    {
      "id": "3",
      "text": "Crear docs/README.md como índice principal de documentación",
      "completed": true
    },
    {
      "id": "4",
      "text": "Actualizar referencias internas entre documentos",
      "completed": true
    },
    {
      "id": "5",
      "text": "Verificar que enlaces externos no se rompan",
      "completed": true
    },
    {
      "id": "6",
      "text": "Actualizar task-004 y task-025 como completadas/cerradas",
      "completed": true
    }
  ],
  "estimatedPoints": 3,
  "estimatedDate": "2025-07-19",
  "images": [],
  "createdAt": "2025-07-19T16:30:00Z",
  "updatedAt": "2025-07-19T21:30:00Z"
}
